{"expireTime":9007200844883866000,"key":"create-remote-file-node-https://cdn.shopify.com/s/files/1/0267/0631/3306/products/H1c94c909e86346d3bf55c2bf6f576fc5m.png","val":{"connection":"close","content-length":"1201438","content-type":"image/png","cache-control":"public, max-age=31557600","expires":"Tue, 18 May 2021 12:58:29 GMT","last-modified":"Mon, 18 May 2020 12:58:29 GMT","edge-cache-tag":"mime-image/png,source-GcsShopAssetsBackend,segment2-188,segment4-48335,revision-b1783964313f23c6ed0e0c27a3cb3130bb297e02,cdn-shopify-com-s-files-1-0267-0631-3306-products-H1c94c909e86346d3bf55c2bf6f576fc5m-png,shop-26706313306","x-image":"proxied_with_processing","x-request-id":"b2e624e577a9f58db273826ba36b2f4f0df980c5f839a6572b9cb45e044fa7e6","access-control-allow-origin":"*","timing-allow-origin":"*","x-xss-protection":"1; mode=block","x-content-type-options":"nosniff","link":"<https://cdn.shopify.com/s/files/1/0267/0631/3306/products/H1c94c909e86346d3bf55c2bf6f576fc5m.png>; rel=\"canonical\"","strict-transport-security":"max-age=63072000; includeSubDomains; preload","x-dc":"gke","x-url":"/s/files/1/0267/0631/3306/products/H1c94c909e86346d3bf55c2bf6f576fc5m.png","accept-ranges":"bytes","date":"Fri, 22 May 2020 10:20:39 GMT","server":"cache-lhr7370-LHR","x-cdn":"Fastly, http1","x-served-by":"cache-lga21923-LGA, cache-lhr7370-LHR","x-cache":"MISS, HIT","x-cache-hits":"0, 1","x-timer":"S1590142840.726021,VS0,VE8","vary":"Accept"}}